LICENSE
README.md
setup.py
santimPay/__init__.py
santimPay/config.py
santimPay/main.py
santimPay.egg-info/PKG-INFO
santimPay.egg-info/SOURCES.txt
santimPay.egg-info/dependency_links.txt
santimPay.egg-info/requires.txt
santimPay.egg-info/top_level.txt
santimPay/core/__init__.py
santimPay/core/santimpay_checkout.py
santimPay/core/santimpay_directpay.py
santimPay/core/direct_pay/__init__.py
santimPay/core/direct_pay/santimpay_direct.py
santimPay/exceptions/__init__.py
santimPay/exceptions/santimpay_exceptions.py
santimPay/types/__init__.py
santimPay/types/api_checkout_request.py
santimPay/types/api_checkout_response.py
santimPay/types/api_checkout_session.py
santimPay/types/api_options.py
santimPay/types/api_response.py
santimPay/types/api_transaction.py
santimPay/types/api_transfer_response.py